.bumpversion.cfg
.cookiecutterrc
.coveragerc
.editorconfig
.gitignore
.travis.yml
AUTHORS.rst
CHANGELOG.rst
CONTRIBUTING.rst
LICENSE
MANIFEST.in
README.rst
setup.cfg
setup.py
tox.ini
ci/bootstrap.py
ci/templates/.travis.yml
docs/authors.rst
docs/changelog.rst
docs/conf.py
docs/contributing.rst
docs/index.rst
docs/installation.rst
docs/readme.rst
docs/requirements.txt
docs/spelling_wordlist.txt
docs/usage.rst
docs/reference/index.rst
docs/reference/topock.rst
src/topock/__init__.py
src/topock/__main__.py
src/topock/cli.py
src/topock.egg-info/PKG-INFO
src/topock.egg-info/SOURCES.txt
src/topock.egg-info/dependency_links.txt
src/topock.egg-info/entry_points.txt
src/topock.egg-info/not-zip-safe
src/topock.egg-info/top_level.txt
tests/test_topock.py